[{"content":"入学健康证明\n","permalink":"https://ban-zheng.github.io/post/binglimoban9834/","summary":"入学健康证明","title":"入学健康证明"},{"content":"诊断证明书病历手指受伤\n","permalink":"https://ban-zheng.github.io/post/binglimoban345435/","summary":"诊断证明书病历手指受伤","title":"诊断证明书病历手指受伤"},{"content":"诊断证明书医疗证明(感冒咳嗽)\n","permalink":"https://ban-zheng.github.io/post/bingli34565761/","summary":"诊断证明书医疗证明(感冒咳嗽)","title":"诊断证明书医疗证明(感冒咳嗽)"},{"content":"诊断证明书病历感冒中医\n","permalink":"https://ban-zheng.github.io/post/bingli345654gr/","summary":"诊断证明书病历感冒中医","title":"诊断证明书病历感冒中医"},{"content":"医院诊断证明书\n","permalink":"https://ban-zheng.github.io/post/binglimoban9877/","summary":"医院诊断证明书","title":"医院诊断证明书病历模板"},{"content":" title: \u0026ldquo;诊断证明书样本病历(呕吐腹泻)模板\u0026rdquo; date: 2023-05-11T01:37:56+08:00\nweight: 1 aliases: [\u0026quot;/first\u0026quot;] tags: [\u0026ldquo;样本\u0026rdquo;,\u0026ldquo;病历\u0026rdquo;,\u0026ldquo;请假条\u0026rdquo;,\u0026ldquo;模板\u0026rdquo;] author: \u0026ldquo;admin\u0026rdquo;\nauthor: [\u0026ldquo;admin\u0026rdquo;, \u0026ldquo;You\u0026rdquo;] # multiple authors showToc: true TocOpen: false draft: false hidemeta: false comments: false\ndescription: \u0026ldquo;Desc Text.\u0026rdquo; canonicalURL: \u0026ldquo;https://canonical.url/to/page\u0026quot; disableHLJS: true # to disable highlightjs disableShare: false disableHLJS: false hideSummary: false searchHidden: false ShowReadingTime: false ShowBreadCrumbs: true ShowPostNavLinks: true ShowWordCount: false ShowRssButtonInSectionTermList: true UseHugoToc: true\ncover: image: \u0026ldquo;\u0026lt;image path/url\u0026gt;\u0026rdquo; # image path/url alt: \u0026ldquo;\u0026rdquo; # alt text caption: \u0026ldquo;\u0026rdquo; # display caption under cover relative: false # when using page bundles set this to true hidden: true # only hide on current single page editPost: URL: \u0026ldquo;https://github.com/\u0026lt;path_to_repo\u0026gt;/content\u0026rdquo; Text: \u0026ldquo;Suggest Changes\u0026rdquo; # edit text appendFilePath: true # to append file path to Edit link XXXXXXXXXXXXXXXXXXXXXXXXXXXX\n","permalink":"https://ban-zheng.github.io/post/1/","summary":"title: \u0026ldquo;诊断证明书样本病历(呕吐腹泻)模板\u0026rdquo; date: 2023-05-11T01:37:56+08:00\nweight: 1 aliases: [\u0026quot;/first\u0026quot;] tags: [\u0026ldquo;样本\u0026rdquo;,\u0026ldquo;病历\u0026rdquo;,\u0026ldquo;请假条\u0026rdquo;,\u0026ldquo;模板\u0026rdquo;] author: \u0026ldquo;admin\u0026rdquo;\nauthor: [\u0026ldquo;admin\u0026rdquo;, \u0026ldquo;You\u0026rdquo;] # multiple authors showToc: true TocOpen: false draft: false hidemeta: false comments: false\ndescription: \u0026ldquo;Desc Text.\u0026rdquo; canonicalURL: \u0026ldquo;https://canonical.url/to/page\u0026quot; disableHLJS: true # to disable highlightjs disableShare: false disableHLJS: false hideSummary: false searchHidden: false ShowReadingTime: false ShowBreadCrumbs: true ShowPostNavLinks: true ShowWordCount: false ShowRssButtonInSectionTermList: true UseHugoToc: true\ncover: image: \u0026ldquo;\u0026lt;image path/url\u0026gt;\u0026rdquo; # image path/url alt: \u0026ldquo;\u0026rdquo; # alt text caption: \u0026ldquo;\u0026rdquo; # display caption under cover relative: false # when using page bundles set this to true hidden: true # only hide on current single page editPost: URL: \u0026ldquo;https://github.","title":"哪里可以输诊断证明书"},{"content":"医院诊断证明书，呕吐腹泻证明代开\n","permalink":"https://ban-zheng.github.io/post/bingli2344/","summary":"医院诊断证明书，呕吐腹泻证明代开","title":"诊断证明书样本病历(呕吐腹泻)模板"},{"content":"B超样本彩超模板早孕B超孕妇怀孕B超\n","permalink":"https://ban-zheng.github.io/post/b-ultrasound/","summary":"B超样本彩超模板早孕B超孕妇怀孕B超","title":"B超彩超早孕孕妇怀孕"},{"content":"专业定制各种排版、P图改字、办证、刻章、病历请假条\u0026hellip; \u0026hellip;\n","permalink":"https://ban-zheng.github.io/about/","summary":"专业定制各种排版、P图改字、办证、刻章、病历请假条\u0026hellip; \u0026hellip;","title":"关于"},{"content":"医院诊断证明书\n","permalink":"https://ban-zheng.github.io/post/bingli2356755/","summary":"医院诊断证明书","title":"诊断证明书病历(呕吐腹泻)模板"}]